vscvm/__init__.py
vscvm/__main__.py
vscvm-1.5.0.dist-info/LICENSE
vscvm-1.5.0.dist-info/METADATA
vscvm-1.5.0.dist-info/WHEEL
vscvm-1.5.0.dist-info/entry_points.txt
vscvm-1.5.0.dist-info/top_level.txt
vscvm-1.5.0.dist-info/RECORD
